d11p/__init__.py
d11p/example.py
d11p-0.0.7.dist-info/LICENSE
d11p-0.0.7.dist-info/METADATA
d11p-0.0.7.dist-info/WHEEL
d11p-0.0.7.dist-info/top_level.txt
d11p-0.0.7.dist-info/RECORD
